django_rename_app/__init__.py
django_rename_app/management/__init__.py
django_rename_app/management/commands/__init__.py
django_rename_app/management/commands/rename_app.py
django_rename_app-0.1.7.dist-info/LICENSE
django_rename_app-0.1.7.dist-info/METADATA
django_rename_app-0.1.7.dist-info/WHEEL
django_rename_app-0.1.7.dist-info/top_level.txt
django_rename_app-0.1.7.dist-info/RECORD
