Metadata-Version: 2.1
Name: django_rename_app
Version: 0.1.7
Summary: A Django Management Command to rename existing Django Applications.
Home-page: https://github.com/odwyersoftware/django-rename-app
Author: O'Dwyer Software
Author-email: hello@odwyer.software
License: Apache 2.0
Classifier: Intended Audience :: Developers
Classifier: Operating System :: OS Independent
Classifier: Programming Language :: Python
Classifier: Programming Language :: Python :: 3
License-File: LICENSE
Requires-Dist: django
